CHANGES.txt
COPYRIGHT.txt
LICENSE.txt
MANIFEST.in
README.txt
setup.cfg
setup.py
src/cykooz/__init__.py
src/cykooz.recipe.pastewsgi.egg-info/PKG-INFO
src/cykooz.recipe.pastewsgi.egg-info/SOURCES.txt
src/cykooz.recipe.pastewsgi.egg-info/dependency_links.txt
src/cykooz.recipe.pastewsgi.egg-info/entry_points.txt
src/cykooz.recipe.pastewsgi.egg-info/namespace_packages.txt
src/cykooz.recipe.pastewsgi.egg-info/not-zip-safe
src/cykooz.recipe.pastewsgi.egg-info/requires.txt
src/cykooz.recipe.pastewsgi.egg-info/top_level.txt
src/cykooz/recipe/__init__.py
src/cykooz/recipe/pastewsgi/__init__.py
src/cykooz/recipe/pastewsgi/recipe.txt
src/cykooz/recipe/pastewsgi/tests.py