Metadata-Version: 1.1
Name: cykooz.recipe.pastewsgi
Version: 0.5
Summary: Buildout recipe to create paste.deploy entry points for mod_wsgi or uwsgi
Home-page: https://bitbucket.org/cykooz/cykooz.recipe.pastewsgi
Author: Cykooz
Author-email: saikuz@mail.ru
License: GPL 2
Platform: UNKNOWN
Classifier: Framework :: Buildout
Classifier: Intended Audience :: Developers
Classifier: Intended Audience :: System Administrators
Classifier: License :: OSI Approved :: GNU General Public License (GPL)
Classifier: Programming Language :: Python
